drt_sdk_cli/__init__.py
drt_sdk_cli/accounts.py
drt_sdk_cli/cli.py
drt_sdk_cli/cli_accounts.py
drt_sdk_cli/cli_config.py
drt_sdk_cli/cli_contracts.py
drt_sdk_cli/cli_data.py
drt_sdk_cli/cli_delegation.py
drt_sdk_cli/cli_deps.py
drt_sdk_cli/cli_dns.py
drt_sdk_cli/cli_ledger.py
drt_sdk_cli/cli_localnet.py
drt_sdk_cli/cli_output.py
drt_sdk_cli/cli_password.py
drt_sdk_cli/cli_shared.py
drt_sdk_cli/cli_transactions.py
drt_sdk_cli/cli_validators.py
drt_sdk_cli/cli_wallet.py
drt_sdk_cli/config.py
drt_sdk_cli/constants.py
drt_sdk_cli/contract_verification.py
drt_sdk_cli/contracts.py
drt_sdk_cli/cosign_transaction.py
drt_sdk_cli/custom_network_provider.py
drt_sdk_cli/dependency_checker.py
drt_sdk_cli/dns.py
drt_sdk_cli/docker.py
drt_sdk_cli/downloader.py
drt_sdk_cli/errors.py
drt_sdk_cli/guards.py
drt_sdk_cli/interfaces.py
drt_sdk_cli/myprocess.py
drt_sdk_cli/sign_verify.py
drt_sdk_cli/simulation.py
drt_sdk_cli/transactions.py
drt_sdk_cli/utils.py
drt_sdk_cli/ux.py
drt_sdk_cli/version.py
drt_sdk_cli/workstation.py
drt_sdk_cli/.vscode/settings.json
drt_sdk_cli/delegation/__init__.py
drt_sdk_cli/delegation/staking_provider.py
drt_sdk_cli/dependencies/__init__.py
drt_sdk_cli/dependencies/install.py
drt_sdk_cli/dependencies/modules.py
drt_sdk_cli/dependencies/resolution.py
drt_sdk_cli/ledger/__init__.py
drt_sdk_cli/ledger/config.py
drt_sdk_cli/ledger/ledger_app_handler.py
drt_sdk_cli/ledger/ledger_functions.py
drt_sdk_cli/localnet/__init__.py
drt_sdk_cli/localnet/config_default.py
drt_sdk_cli/localnet/config_general.py
drt_sdk_cli/localnet/config_networking.py
drt_sdk_cli/localnet/config_part.py
drt_sdk_cli/localnet/config_root.py
drt_sdk_cli/localnet/config_sharding.py
drt_sdk_cli/localnet/config_software.py
drt_sdk_cli/localnet/constants.py
drt_sdk_cli/localnet/genesis.py
drt_sdk_cli/localnet/genesis_json.py
drt_sdk_cli/localnet/genesis_smart_contracts_json.py
drt_sdk_cli/localnet/libraries.py
drt_sdk_cli/localnet/node.py
drt_sdk_cli/localnet/node_config_toml.py
drt_sdk_cli-0.0.1.dist-info/METADATA
drt_sdk_cli-0.0.1.dist-info/WHEEL
drt_sdk_cli-0.0.1.dist-info/entry_points.txt
drt_sdk_cli-0.0.1.dist-info/licenses/LICENSE
drt_sdk_cli-0.0.1.dist-info/RECORD
