Metadata-Version: 2.3
Name: drt-sdk-cli
Version: 0.0.1
Summary: Dharitri Smart Contracts Tools
Project-URL: Homepage, https://github.com/DharitriOne/drt-sdk-py-cli
Author: Dharitri
License-Expression: MIT
License-File: LICENSE
Classifier: Intended Audience :: Developers
Classifier: License :: OSI Approved :: MIT License
Classifier: Operating System :: OS Independent
Classifier: Programming Language :: Python :: 3
Requires-Python: >=3.8
Requires-Dist: drt-sdk-core<0.1.0,>=0.0.1
Requires-Dist: drt-sdk-network-providers<0.1.0,>=0.0.1
Requires-Dist: drt-sdk-wallet<0.1.0,>=0.0.1
Requires-Dist: ledgercomm[hid]
Requires-Dist: prettytable
Requires-Dist: requests
Requires-Dist: requests-cache
Requires-Dist: rich==13.3.4
Requires-Dist: semver
Requires-Dist: toml>=0.10.2
